symbolconnectors/__init__.py
symbolconnectors/bindings/.gitignore
symbolconnectors/bindings/__init__.py
symbolconnectors/bindings/openssl.py
symbolconnectors/connector/BasicConnector.py
symbolconnectors/connector/CatapultCertificateProcessor.py
symbolconnectors/connector/CertificateUtils.py
symbolconnectors/connector/NemConnector.py
symbolconnectors/connector/SymbolConnector.py
symbolconnectors/connector/SymbolPeerConnector.py
symbolconnectors/connector/__init__.py
symbolconnectors/model/Endpoint.py
symbolconnectors/model/Exceptions.py
symbolconnectors/model/NodeInfo.py
symbolconnectors/model/PacketHeader.py
symbolconnectors/model/__init__.py
symbol_connectors-0.0.2.dist-info/METADATA
symbol_connectors-0.0.2.dist-info/WHEEL
symbol_connectors-0.0.2.dist-info/RECORD
