Metadata-Version: 2.1
Name: symbol-connectors
Version: 0.0.2
Summary: Symbol Connectors
Home-page: https://github.com/symbol/product/tree/main/python/connectors
License: MIT
Keywords: symbol,connectors,Symbol Connectors
Author: Symbol Contributors
Author-email: contributors@symbol.dev
Maintainer: Symbol Contributors
Maintainer-email: contributors@symbol.dev
Requires-Python: >=3.7,<4.0
Classifier: License :: OSI Approved :: MIT License
Classifier: Programming Language :: Python :: 3
Classifier: Programming Language :: Python :: 3.7
Classifier: Programming Language :: Python :: 3.8
Classifier: Programming Language :: Python :: 3.9
Classifier: Programming Language :: Python :: 3.10
Classifier: Programming Language :: Python :: 3.11
Classifier: Programming Language :: Python :: 3.7
Requires-Dist: aiohttp (==3.8.4)
Requires-Dist: symbol-sdk-python (==3.0.7)
Requires-Dist: zenlog (==1.1)
Project-URL: Repository, https://github.com/symbol/product/tree/main/python/connectors
